document_parse/__init__.py
document_parse/llamaparse.py
document_parse/main_file_s3_to_llamaparse.py
mcp_crew/__init__.py
mcp_crew/__main__.py
mcp_crew/constants.py
mcp_crew/databases.py
mcp_crew/generate_mail_html.py
mcp_crew/html_link_from_md.py
mcp_crew/prompts.py
mcp_crew/resources.py
mcp_crew/server.py
mcp_crew/tool_schema.py
mcp_crew/tools.py
mcp_crew/Agent/main.py
mcp_crew/Agent/markdown_logger.py
mcp_crew/Agent/setup.py
mcp_crew/Agent/app/__init__.py
mcp_crew/Agent/app/bedrock.py
mcp_crew/Agent/app/config.py
mcp_crew/Agent/app/exceptions.py
mcp_crew/Agent/app/llm.py
mcp_crew/Agent/app/logger.py
mcp_crew/Agent/app/schema.py
mcp_crew/Agent/app/toolHandler.py
mcp_crew/Agent/app/agent/__init__.py
mcp_crew/Agent/app/agent/base.py
mcp_crew/Agent/app/agent/casefileAgent.py
mcp_crew/Agent/app/agent/react.py
mcp_crew/Agent/app/agent/toolcall.py
mcp_crew/Agent/app/sandbox/__init__.py
mcp_crew/Agent/app/sandbox/client.py
mcp_crew/Agent/app/sandbox/core/exceptions.py
mcp_crew/Agent/app/sandbox/core/manager.py
mcp_crew/Agent/app/sandbox/core/sandbox.py
mcp_crew/Agent/app/sandbox/core/terminal.py
mcp_crew/Agent/app/tool/__init__.py
mcp_crew/Agent/app/tool/base.py
mcp_crew/Agent/app/tool/create_chat_completion.py
mcp_crew/Agent/app/tool/mcp_tool.py
mcp_crew/Agent/app/tool/terminate.py
mcp_crew/Agent/app/tool/tool_collection.py
mcp_crew/Agent/app/tool/search/__init__.py
mcp_crew/Agent/app/tool/search/baidu_search.py
mcp_crew/Agent/app/tool/search/base.py
mcp_crew/Agent/app/tool/search/bing_search.py
mcp_crew/Agent/app/tool/search/duckduckgo_search.py
mcp_crew/Agent/app/tool/search/google_search.py
mcp_crew/Agent/app/tool/search/vessel_database_search.py
mcp_crew/Agent/app/tool/search/vessel_search.py
mcp_crew/Agent/config/config.toml
mcp_crew/Agent/config/mcp_servers_config.json
mcp_crew/Agent/config/tools.json
mcp_crew/scheduler/executor.py
mcp_crew/scheduler/schedule.py
utils/__init__.py
utils/llm.py
syia_mcp_crew_2025_x7k9-0.1.18.dist-info/METADATA
syia_mcp_crew_2025_x7k9-0.1.18.dist-info/WHEEL
syia_mcp_crew_2025_x7k9-0.1.18.dist-info/top_level.txt
syia_mcp_crew_2025_x7k9-0.1.18.dist-info/RECORD
